{
  "date": "2025-07-19",
  "totalPlayerTrophies": 172234,
  "members": [
    {
      "name": "\u26a1\ufe0fBENIMARU\u26a1\ufe0f",
      "tag": "#YUJLJ2V8Y",
      "position": 1,
      "trophies": 5588
    },
    {
      "name": "\u24c2\ufe0fBIG COCHY3\u24c2\ufe0f",
      "tag": "#9U2YP0RY",
      "position": 2,
      "trophies": 4986
    },
    {
      "name": "Chopsticks",
      "tag": "#QPQGQCR2U",
      "position": 3,
      "trophies": 4977
    },
    {
      "name": "\u2b50\u2b505 StarFree\u2b50\u2b50\u2b50",
      "tag": "#Y2PVPPU8C",
      "position": 4,
      "trophies": 4972
    },
    {
      "name": "je suis excit\u00e9",
      "tag": "#Q9QU8L8YV",
      "position": 5,
      "trophies": 4971
    },
    {
      "name": "THUNDERER.THOR",
      "tag": "#9U0VYLP0Q",
      "position": 6,
      "trophies": 4946
    },
    {
      "name": "Sir Walnut\u2122\ufe0f",
      "tag": "#YQ8L9JVJ2",
      "position": 7,
      "trophies": 4908
    },
    {
      "name": "Phantom",
      "tag": "#LYJJ9PLV9",
      "position": 8,
      "trophies": 4903
    },
    {
      "name": "ScreaM-iwnl-",
      "tag": "#9L9G0P92V",
      "position": 9,
      "trophies": 4899
    },
    {
      "name": "destroyer",
      "tag": "#UJP2UYRY",
      "position": 10,
      "trophies": 4819
    },
    {
      "name": "Aerystockrat",
      "tag": "#G2R9YGCP9",
      "position": 11,
      "trophies": 4814
    },
    {
      "name": "Master Baker",
      "tag": "#GU9YPRYJ",
      "position": 12,
      "trophies": 4784
    },
    {
      "name": "dipranjan",
      "tag": "#YJUYGR9GP",
      "position": 13,
      "trophies": 4754
    },
    {
      "name": "Swift",
      "tag": "#PRGGL2J2V",
      "position": 14,
      "trophies": 4659
    },
    {
      "name": "Edison123",
      "tag": "#9VU0VU90G",
      "position": 15,
      "trophies": 4434
    },
    {
      "name": "JLai",
      "tag": "#GLU9LC2LG",
      "position": 16,
      "trophies": 4401
    },
    {
      "name": "CARTI",
      "tag": "#9GVLUGLGY",
      "position": 17,
      "trophies": 4390
    },
    {
      "name": "alphachupapa",
      "tag": "#G09YYYRLY",
      "position": 18,
      "trophies": 4384
    },
    {
      "name": "Cookies",
      "tag": "#LCUL88JLG",
      "position": 19,
      "trophies": 4373
    },
    {
      "name": "bmuff2002",
      "tag": "#V0JYCPRR",
      "position": 20,
      "trophies": 4361
    },
    {
      "name": "SPIRIToFbANANA",
      "tag": "#2JJ2PR9VL",
      "position": 21,
      "trophies": 4214
    },
    {
      "name": "Sir Chestnut\u2122\ufe0f",
      "tag": "#8VQYULVQQ",
      "position": 22,
      "trophies": 4126
    },
    {
      "name": "mony",
      "tag": "#RPUUGRUC",
      "position": 23,
      "trophies": 4021
    },
    {
      "name": "Sir Hazelnut\u2122\ufe0f",
      "tag": "#YJ2UV2GY",
      "position": 24,
      "trophies": 3962
    },
    {
      "name": "Usermj",
      "tag": "#9JY0PL8UG",
      "position": 25,
      "trophies": 3934
    },
    {
      "name": "Gladiator",
      "tag": "#LY0QGPJC2",
      "position": 26,
      "trophies": 3695
    },
    {
      "name": "Assasinator",
      "tag": "#289QYU90",
      "position": 27,
      "trophies": 3620
    },
    {
      "name": "peter qiu rocks",
      "tag": "#8RJ28GQ2",
      "position": 28,
      "trophies": 3619
    },
    {
      "name": "TheRealRHZ",
      "tag": "#YJ09R8L0P",
      "position": 29,
      "trophies": 3602
    },
    {
      "name": "JT",
      "tag": "#QRP2RLV02",
      "position": 30,
      "trophies": 3475
    },
    {
      "name": "Smog",
      "tag": "#YVGGJLPRJ",
      "position": 31,
      "trophies": 3387
    },
    {
      "name": "King Killer",
      "tag": "#J88YJGY9",
      "position": 32,
      "trophies": 3340
    },
    {
      "name": "Sushant Bhaita",
      "tag": "#Q0YQURYCY",
      "position": 33,
      "trophies": 3287
    },
    {
      "name": "Badboy101",
      "tag": "#RUVPQQR0",
      "position": 34,
      "trophies": 3200
    },
    {
      "name": "Mac and Cheeks",
      "tag": "#L80PYCRV8",
      "position": 35,
      "trophies": 3150
    },
    {
      "name": "arvin",
      "tag": "#228J9V02L",
      "position": 36,
      "trophies": 3138
    },
    {
      "name": "p\u00e9p\u00e9111147",
      "tag": "#LVQCVGR2",
      "position": 37,
      "trophies": 3028
    },
    {
      "name": "ChampionHZ",
      "tag": "#YU00CRCUG",
      "position": 38,
      "trophies": 2970
    },
    {
      "name": "master darsh",
      "tag": "#JCJ9V8V",
      "position": 39,
      "trophies": 2829
    },
    {
      "name": "JSomeGuy",
      "tag": "#QGLJCPU8G",
      "position": 40,
      "trophies": 2812
    },
    {
      "name": "Aurelian",
      "tag": "#GGYGQ8098",
      "position": 41,
      "trophies": 2584
    },
    {
      "name": "matt",
      "tag": "#L00U90C0P",
      "position": 42,
      "trophies": 2493
    },
    {
      "name": "Ryan",
      "tag": "#2920V9PV",
      "position": 43,
      "trophies": 2425
    }
  ]
}