{
  "state": "inWar",
  "teamSize": 30,
  "attacksPerMember": 2,
  "battleModifier": "none",
  "preparationStartTime": "20250824T140224.000Z",
  "startTime": "20250825T130224.000Z",
  "endTime": "20250826T130224.000Z",
  "clan": {
    "tag": "#2GRPGV0VL",
    "name": "July",
    "badgeUrls": {
      "small": "https://api-assets.clashofclans.com/badges/70/SDaPAleElDurilJwEJ4hTNB9YR3pRupEbuncsdoGpvc.png",
      "large": "https://api-assets.clashofclans.com/badges/512/SDaPAleElDurilJwEJ4hTNB9YR3pRupEbuncsdoGpvc.png",
      "medium": "https://api-assets.clashofclans.com/badges/200/SDaPAleElDurilJwEJ4hTNB9YR3pRupEbuncsdoGpvc.png"
    },
    "clanLevel": 9,
    "attacks": 45,
    "stars": 83,
    "destructionPercentage": 95.3,
    "members": [
      {
        "tag": "#RUVPQQR0",
        "name": "Badboy101",
        "townhallLevel": 13,
        "mapPosition": 28,
        "attacks": [
          {
            "attackerTag": "#RUVPQQR0",
            "defenderTag": "#9VRLVPPYQ",
            "stars": 3,
            "destructionPercentage": 100,
            "order": 38,
            "duration": 144
          },
          {
            "attackerTag": "#RUVPQQR0",
            "defenderTag": "#YUUGYLL8",
            "stars": 2,
            "destructionPercentage": 61,
            "order": 39,
            "duration": 98
          }
        ],
        "opponentAttacks": 1,
        "bestOpponentAttack": {
          "attackerTag": "#9VGCJC0GC",
          "defenderTag": "#RUVPQQR0",
          "stars": 3,
          "destructionPercentage": 100,
          "order": 34,
          "duration": 158
        }
      },
      {
        "tag": "#UJP2UYRY",
        "name": "destroyer",
        "townhallLevel": 16,
        "mapPosition": 3,
        "attacks": [
          {
            "attackerTag": "#UJP2UYRY",
            "defenderTag": "#QLJ888P0",
            "stars": 3,
            "destructionPercentage": 100,
            "order": 43,
            "duration": 113
          },
          {
            "attackerTag": "#UJP2UYRY",
            "defenderTag": "#GJJJJ8QJ2",
            "stars": 3,
            "destructionPercentage": 100,
            "order": 45,
            "duration": 73
          }
        ],
        "opponentAttacks": 2,
        "bestOpponentAttack": {
          "attackerTag": "#8LUYJYPLV",
          "defenderTag": "#UJP2UYRY",
          "stars": 3,
          "destructionPercentage": 100,
          "order": 55,
          "duration": 87
        }
      },
      {
        "tag": "#GLU9LC2LG",
        "name": "JLai",
        "townhallLevel": 14,
        "mapPosition": 16,
        "attacks": [
          {
            "attackerTag": "#GLU9LC2LG",
            "defenderTag": "#2VYP99Q0",
            "stars": 2,
            "destructionPercentage": 94,
            "order": 7,
            "duration": 180
          },
          {
            "attackerTag": "#GLU9LC2LG",
            "defenderTag": "#L8L0U9QJL",
            "stars": 3,
            "destructionPercentage": 100,
            "order": 14,
            "duration": 145
          }
        ],
        "opponentAttacks": 2,
        "bestOpponentAttack": {
          "attackerTag": "#2UYQQ288J",
          "defenderTag": "#GLU9LC2LG",
          "stars": 3,
          "destructionPercentage": 100,
          "order": 67,
          "duration": 167
        }
      },
      {
        "tag": "#2920V9PV",
        "name": "Ryan",
        "townhallLevel": 14,
        "mapPosition": 17,
        "attacks": [
          {
            "attackerTag": "#2920V9PV",
            "defenderTag": "#YP9Y8U0QC",
            "stars": 2,
            "destructionPercentage": 52,
            "order": 35,
            "duration": 90
          },
          {
            "attackerTag": "#2920V9PV",
            "defenderTag": "#QQUPP29VC",
            "stars": 2,
            "destructionPercentage": 87,
            "order": 40,
            "duration": 128
          }
        ],
        "opponentAttacks": 1,
        "bestOpponentAttack": {
          "attackerTag": "#2JG8G0GUC",
          "defenderTag": "#2920V9PV",
          "stars": 3,
          "destructionPercentage": 100,
          "order": 30,
          "duration": 133
        }
      },
      {
        "tag": "#Q0YQURYCY",
        "name": "Sushant Bhaita",
        "townhallLevel": 14,
        "mapPosition": 23,
        "attacks": [
          {
            "attackerTag": "#Q0YQURYCY",
            "defenderTag": "#YC2Q220G",
            "stars": 2,
            "destructionPercentage": 52,
            "order": 36,
            "duration": 93
          },
          {
            "attackerTag": "#Q0YQURYCY",
            "defenderTag": "#9QC0YY9J8",
            "stars": 1,
            "destructionPercentage": 45,
            "order": 37,
            "duration": 73
          }
        ],
        "opponentAttacks": 2,
        "bestOpponentAttack": {
          "attackerTag": "#2VYP99Q0",
          "defenderTag": "#Q0YQURYCY",
          "stars": 3,
          "destructionPercentage": 100,
          "order": 86,
          "duration": 96
        }
      },
      {
        "tag": "#Q9QU8L8YV",
        "name": "je suis excit\u00e9",
        "townhallLevel": 16,
        "mapPosition": 6,
        "attacks": [
          {
            "attackerTag": "#Q9QU8L8YV",
            "defenderTag": "#PGPQCCVJ",
            "stars": 3,
            "destructionPercentage": 100,
            "order": 44,
            "duration": 165
          },
          {
            "attackerTag": "#Q9QU8L8YV",
            "defenderTag": "#9CRY00G00",
            "stars": 3,
            "destructionPercentage": 100,
            "order": 47,
            "duration": 162
          }
        ],
        "opponentAttacks": 2,
        "bestOpponentAttack": {
          "attackerTag": "#8LUYJYPLV",
          "defenderTag": "#Q9QU8L8YV",
          "stars": 3,
          "destructionPercentage": 100,
          "order": 56,
          "duration": 64
        }
      },
      {
        "tag": "#V0JYCPRR",
        "name": "bmuff2002",
        "townhallLevel": 13,
        "mapPosition": 29,
        "attacks": [
          {
            "attackerTag": "#V0JYCPRR",
            "defenderTag": "#P290YCJ2L",
            "stars": 1,
            "destructionPercentage": 98,
            "order": 41,
            "duration": 180
          },
          {
            "attackerTag": "#V0JYCPRR",
            "defenderTag": "#YUUGYLL8",
            "stars": 2,
            "destructionPercentage": 82,
            "order": 77,
            "duration": 155
          }
        ],
        "opponentAttacks": 1,
        "bestOpponentAttack": {
          "attackerTag": "#9VRLVPPYQ",
          "defenderTag": "#V0JYCPRR",
          "stars": 3,
          "destructionPercentage": 100,
          "order": 5,
          "duration": 106
        }
      },
      {
        "tag": "#Q2QQL2YVV",
        "name": "cyan",
        "townhallLevel": 14,
        "mapPosition": 24,
        "attacks": [
          {
            "attackerTag": "#Q2QQL2YVV",
            "defenderTag": "#QYCYV9Q2G",
            "stars": 3,
            "destructionPercentage": 100,
            "order": 50,
            "duration": 127
          },
          {
            "attackerTag": "#Q2QQL2YVV",
            "defenderTag": "#QVGUGCL2",
            "stars": 2,
            "destructionPercentage": 90,
            "order": 51,
            "duration": 143
          }
        ],
        "opponentAttacks": 3,
        "bestOpponentAttack": {
          "attackerTag": "#2VYP99Q0",
          "defenderTag": "#Q2QQL2YVV",
          "stars": 3,
          "destructionPercentage": 100,
          "order": 84,
          "duration": 146
        }
      },
      {
        "tag": "#9U2YP0RY",
        "name": "\u24c2\ufe0fBIG COCHY3\u24c2\ufe0f",
        "townhallLevel": 15,
        "mapPosition": 5,
        "attacks": [
          {
            "attackerTag": "#9U2YP0RY",
            "defenderTag": "#2QG8JYCGG",
            "stars": 3,
            "destructionPercentage": 100,
            "order": 68,
            "duration": 73
          },
          {
            "attackerTag": "#9U2YP0RY",
            "defenderTag": "#2JG8G0GUC",
            "stars": 3,
            "destructionPercentage": 100,
            "order": 71,
            "duration": 99
          }
        ],
        "opponentAttacks": 1,
        "bestOpponentAttack": {
          "attackerTag": "#280Y2VPL2",
          "defenderTag": "#9U2YP0RY",
          "stars": 3,
          "destructionPercentage": 100,
          "order": 8,
          "duration": 149
        }
      },
      {
        "tag": "#QVUQ2VR98",
        "name": "William the thi",
        "townhallLevel": 14,
        "mapPosition": 20,
        "attacks": [
          {
            "attackerTag": "#QVUQ2VR98",
            "defenderTag": "#YLUGJYP00",
            "stars": 2,
            "destructionPercentage": 92,
            "order": 53,
            "duration": 112
          },
          {
            "attackerTag": "#QVUQ2VR98",
            "defenderTag": "#P0RRULRP9",
            "stars": 2,
            "destructionPercentage": 76,
            "order": 54,
            "duration": 108
          }
        ],
        "opponentAttacks": 2,
        "bestOpponentAttack": {
          "attackerTag": "#9QC0YY9J8",
          "defenderTag": "#QVUQ2VR98",
          "stars": 3,
          "destructionPercentage": 100,
          "order": 81,
          "duration": 73
        }
      },
      {
        "tag": "#QQUUQYQVL",
        "name": "9/11",
        "townhallLevel": 14,
        "mapPosition": 11,
        "opponentAttacks": 1,
        "bestOpponentAttack": {
          "attackerTag": "#P290YCJ2L",
          "defenderTag": "#QQUUQYQVL",
          "stars": 2,
          "destructionPercentage": 99,
          "order": 22,
          "duration": 180
        }
      },
      {
        "tag": "#YQ8L9JVJ2",
        "name": "Sir Walnut\u2122\ufe0f",
        "townhallLevel": 17,
        "mapPosition": 2,
        "attacks": [
          {
            "attackerTag": "#YQ8L9JVJ2",
            "defenderTag": "#8LUYJYPLV",
            "stars": 3,
            "destructionPercentage": 100,
            "order": 12,
            "duration": 155
          },
          {
            "attackerTag": "#YQ8L9JVJ2",
            "defenderTag": "#280Y2VPL2",
            "stars": 3,
            "destructionPercentage": 100,
            "order": 15,
            "duration": 163
          }
        ],
        "opponentAttacks": 2,
        "bestOpponentAttack": {
          "attackerTag": "#QGCC80GC8",
          "defenderTag": "#YQ8L9JVJ2",
          "stars": 3,
          "destructionPercentage": 100,
          "order": 87,
          "duration": 176
        }
      },
      {
        "tag": "#LYJJ9PLV9",
        "name": "Phantom",
        "townhallLevel": 15,
        "mapPosition": 4,
        "attacks": [
          {
            "attackerTag": "#LYJJ9PLV9",
            "defenderTag": "#L8VG2VC0L",
            "stars": 3,
            "destructionPercentage": 100,
            "order": 69,
            "duration": 163
          },
          {
            "attackerTag": "#LYJJ9PLV9",
            "defenderTag": "#2VYP99Q0",
            "stars": 3,
            "destructionPercentage": 100,
            "order": 90,
            "duration": 160
          }
        ],
        "opponentAttacks": 2,
        "bestOpponentAttack": {
          "attackerTag": "#PGPQCCVJ",
          "defenderTag": "#LYJJ9PLV9",
          "stars": 3,
          "destructionPercentage": 100,
          "order": 25,
          "duration": 139
        }
      },
      {
        "tag": "#PPLULPGVU",
        "name": "devilunni",
        "townhallLevel": 14,
        "mapPosition": 8,
        "opponentAttacks": 1,
        "bestOpponentAttack": {
          "attackerTag": "#9CRY00G00",
          "defenderTag": "#PPLULPGVU",
          "stars": 3,
          "destructionPercentage": 100,
          "order": 4,
          "duration": 142
        }
      },
      {
        "tag": "#LPYV8PPGP",
        "name": "Brayden",
        "townhallLevel": 14,
        "mapPosition": 13,
        "attacks": [
          {
            "attackerTag": "#LPYV8PPGP",
            "defenderTag": "#G2Y8R0QCL",
            "stars": 3,
            "destructionPercentage": 100,
            "order": 31,
            "duration": 141
          }
        ],
        "opponentAttacks": 1,
        "bestOpponentAttack": {
          "attackerTag": "#L8VG2VC0L",
          "defenderTag": "#LPYV8PPGP",
          "stars": 3,
          "destructionPercentage": 100,
          "order": 21,
          "duration": 165
        }
      },
      {
        "tag": "#2QRGJQJ2Q",
        "name": "KingFighter COC",
        "townhallLevel": 14,
        "mapPosition": 19,
        "opponentAttacks": 1,
        "bestOpponentAttack": {
          "attackerTag": "#L8L0U9QJL",
          "defenderTag": "#2QRGJQJ2Q",
          "stars": 3,
          "destructionPercentage": 100,
          "order": 52,
          "duration": 142
        }
      },
      {
        "tag": "#RJULR9R",
        "name": "kingsaxon2000",
        "townhallLevel": 14,
        "mapPosition": 26,
        "opponentAttacks": 1,
        "bestOpponentAttack": {
          "attackerTag": "#YUUGYLL8",
          "defenderTag": "#RJULR9R",
          "stars": 3,
          "destructionPercentage": 100,
          "order": 28,
          "duration": 110
        }
      },
      {
        "tag": "#QVGVJJ99C",
        "name": "FF\u2763\ufe0fGelu",
        "townhallLevel": 14,
        "mapPosition": 14,
        "opponentAttacks": 1,
        "bestOpponentAttack": {
          "attackerTag": "#GJJJJ8QJ2",
          "defenderTag": "#QVGVJJ99C",
          "stars": 3,
          "destructionPercentage": 100,
          "order": 24,
          "duration": 92
        }
      },
      {
        "tag": "#QRP2RLV02",
        "name": "JT",
        "townhallLevel": 14,
        "mapPosition": 25,
        "attacks": [
          {
            "attackerTag": "#QRP2RLV02",
            "defenderTag": "#PP8RGVJY0",
            "stars": 3,
            "destructionPercentage": 100,
            "order": 58,
            "duration": 128
          },
          {
            "attackerTag": "#QRP2RLV02",
            "defenderTag": "#YP9Y8U0QC",
            "stars": 3,
            "destructionPercentage": 100,
            "order": 59,
            "duration": 72
          }
        ],
        "opponentAttacks": 2,
        "bestOpponentAttack": {
          "attackerTag": "#GJJPC9QV",
          "defenderTag": "#QRP2RLV02",
          "stars": 3,
          "destructionPercentage": 100,
          "order": 66,
          "duration": 130
        }
      },
      {
        "tag": "#YRPCLRRLQ",
        "name": "A_Y_K_0",
        "townhallLevel": 14,
        "mapPosition": 12,
        "opponentAttacks": 1,
        "bestOpponentAttack": {
          "attackerTag": "#P290YCJ2L",
          "defenderTag": "#YRPCLRRLQ",
          "stars": 3,
          "destructionPercentage": 100,
          "order": 23,
          "duration": 128
        }
      },
      {
        "tag": "#G28CVVRJL",
        "name": "exofall",
        "townhallLevel": 17,
        "mapPosition": 1,
        "attacks": [
          {
            "attackerTag": "#G28CVVRJL",
            "defenderTag": "#QGCC80GC8",
            "stars": 3,
            "destructionPercentage": 100,
            "order": 3,
            "duration": 144
          },
          {
            "attackerTag": "#G28CVVRJL",
            "defenderTag": "#LP90C2YPP",
            "stars": 3,
            "destructionPercentage": 100,
            "order": 10,
            "duration": 156
          }
        ],
        "opponentAttacks": 1,
        "bestOpponentAttack": {
          "attackerTag": "#QGCC80GC8",
          "defenderTag": "#G28CVVRJL",
          "stars": 2,
          "destructionPercentage": 82,
          "order": 88,
          "duration": 154
        }
      },
      {
        "tag": "#9VU0VU90G",
        "name": "Edison123",
        "townhallLevel": 14,
        "mapPosition": 18,
        "attacks": [
          {
            "attackerTag": "#9VU0VU90G",
            "defenderTag": "#QVGUGCL2",
            "stars": 2,
            "destructionPercentage": 87,
            "order": 73,
            "duration": 180
          },
          {
            "attackerTag": "#9VU0VU90G",
            "defenderTag": "#YUUGYLL8",
            "stars": 2,
            "destructionPercentage": 91,
            "order": 74,
            "duration": 140
          }
        ],
        "opponentAttacks": 2,
        "bestOpponentAttack": {
          "attackerTag": "#9QC0YY9J8",
          "defenderTag": "#9VU0VU90G",
          "stars": 3,
          "destructionPercentage": 100,
          "order": 79,
          "duration": 69
        }
      },
      {
        "tag": "#GGYGQ8098",
        "name": "Aurelian",
        "townhallLevel": 12,
        "mapPosition": 30,
        "attacks": [
          {
            "attackerTag": "#GGYGQ8098",
            "defenderTag": "#9VRLVPPYQ",
            "stars": 1,
            "destructionPercentage": 74,
            "order": 16,
            "duration": 98
          },
          {
            "attackerTag": "#GGYGQ8098",
            "defenderTag": "#9VGCJC0GC",
            "stars": 2,
            "destructionPercentage": 65,
            "order": 17,
            "duration": 135
          }
        ],
        "opponentAttacks": 1,
        "bestOpponentAttack": {
          "attackerTag": "#9VRLVPPYQ",
          "defenderTag": "#GGYGQ8098",
          "stars": 3,
          "destructionPercentage": 100,
          "order": 9,
          "duration": 82
        }
      },
      {
        "tag": "#G9CC9G2VQ",
        "name": "Grizz",
        "townhallLevel": 14,
        "mapPosition": 22,
        "attacks": [
          {
            "attackerTag": "#G9CC9G2VQ",
            "defenderTag": "#9VGCJC0GC",
            "stars": 3,
            "destructionPercentage": 100,
            "order": 57,
            "duration": 110
          },
          {
            "attackerTag": "#G9CC9G2VQ",
            "defenderTag": "#YUUGYLL8",
            "stars": 1,
            "destructionPercentage": 75,
            "order": 61,
            "duration": 115
          }
        ],
        "opponentAttacks": 4,
        "bestOpponentAttack": {
          "attackerTag": "#2QG8JYCGG",
          "defenderTag": "#G9CC9G2VQ",
          "stars": 3,
          "destructionPercentage": 100,
          "order": 92,
          "duration": 72
        }
      },
      {
        "tag": "#9GL0YG0VU",
        "name": "Razib bp",
        "townhallLevel": 14,
        "mapPosition": 10,
        "attacks": [
          {
            "attackerTag": "#9GL0YG0VU",
            "defenderTag": "#2UYQQ288J",
            "stars": 3,
            "destructionPercentage": 100,
            "order": 48,
            "duration": 148
          },
          {
            "attackerTag": "#9GL0YG0VU",
            "defenderTag": "#2JG8G0GUC",
            "stars": 2,
            "destructionPercentage": 97,
            "order": 49,
            "duration": 180
          }
        ],
        "opponentAttacks": 2,
        "bestOpponentAttack": {
          "attackerTag": "#L8VG2VC0L",
          "defenderTag": "#9GL0YG0VU",
          "stars": 2,
          "destructionPercentage": 82,
          "order": 20,
          "duration": 161
        }
      },
      {
        "tag": "#LGGLYVUPP",
        "name": "siwi2isuus2",
        "townhallLevel": 15,
        "mapPosition": 7,
        "attacks": [
          {
            "attackerTag": "#LGGLYVUPP",
            "defenderTag": "#PP8RGVJY0",
            "stars": 1,
            "destructionPercentage": 80,
            "order": 26,
            "duration": 122
          },
          {
            "attackerTag": "#LGGLYVUPP",
            "defenderTag": "#L0QG2V09",
            "stars": 2,
            "destructionPercentage": 90,
            "order": 27,
            "duration": 107
          }
        ],
        "opponentAttacks": 1,
        "bestOpponentAttack": {
          "attackerTag": "#9CRY00G00",
          "defenderTag": "#LGGLYVUPP",
          "stars": 3,
          "destructionPercentage": 100,
          "order": 2,
          "duration": 126
        }
      },
      {
        "tag": "#LCUL88JLG",
        "name": "Cookies",
        "townhallLevel": 14,
        "mapPosition": 15,
        "attacks": [
          {
            "attackerTag": "#LCUL88JLG",
            "defenderTag": "#GJJPC9QV",
            "stars": 3,
            "destructionPercentage": 100,
            "order": 70,
            "duration": 138
          },
          {
            "attackerTag": "#LCUL88JLG",
            "defenderTag": "#9QC0YY9J8",
            "stars": 3,
            "destructionPercentage": 100,
            "order": 72,
            "duration": 147
          }
        ],
        "opponentAttacks": 2,
        "bestOpponentAttack": {
          "attackerTag": "#2JG8G0GUC",
          "defenderTag": "#LCUL88JLG",
          "stars": 2,
          "destructionPercentage": 99,
          "order": 29,
          "duration": 180
        }
      },
      {
        "tag": "#Q9Q0CRR0V",
        "name": "dev_griff7",
        "townhallLevel": 14,
        "mapPosition": 27,
        "attacks": [
          {
            "attackerTag": "#Q9Q0CRR0V",
            "defenderTag": "#P290YCJ2L",
            "stars": 2,
            "destructionPercentage": 55,
            "order": 42,
            "duration": 79
          },
          {
            "attackerTag": "#Q9Q0CRR0V",
            "defenderTag": "#9VGCJC0GC",
            "stars": 2,
            "destructionPercentage": 68,
            "order": 46,
            "duration": 97
          }
        ],
        "opponentAttacks": 2,
        "bestOpponentAttack": {
          "attackerTag": "#YC2Q220G",
          "defenderTag": "#Q9Q0CRR0V",
          "stars": 3,
          "destructionPercentage": 100,
          "order": 78,
          "duration": 118
        }
      },
      {
        "tag": "#LLYV29CU",
        "name": "1rose",
        "townhallLevel": 14,
        "mapPosition": 21,
        "attacks": [
          {
            "attackerTag": "#LLYV29CU",
            "defenderTag": "#QVGUGCL2",
            "stars": 2,
            "destructionPercentage": 92,
            "order": 82,
            "duration": 180
          }
        ],
        "opponentAttacks": 1,
        "bestOpponentAttack": {
          "attackerTag": "#L8L0U9QJL",
          "defenderTag": "#LLYV29CU",
          "stars": 3,
          "destructionPercentage": 100,
          "order": 60,
          "duration": 146
        }
      },
      {
        "tag": "#99JUYVYLC",
        "name": "Bijoy jacob",
        "townhallLevel": 14,
        "mapPosition": 9,
        "attacks": [
          {
            "attackerTag": "#99JUYVYLC",
            "defenderTag": "#P0RRULRP9",
            "stars": 3,
            "destructionPercentage": 100,
            "order": 75,
            "duration": 145
          }
        ],
        "opponentAttacks": 1,
        "bestOpponentAttack": {
          "attackerTag": "#PGPQCCVJ",
          "defenderTag": "#99JUYVYLC",
          "stars": 3,
          "destructionPercentage": 100,
          "order": 18,
          "duration": 127
        }
      }
    ]
  },
  "opponent": {
    "tag": "#2LP92JVGR",
    "name": "Vortex Legion",
    "badgeUrls": {
      "small": "https://api-assets.clashofclans.com/badges/70/qvVyEGEhwIjPx6oL_BYwfcnp_hoVPWhbBaWGJdsAnpQ.png",
      "large": "https://api-assets.clashofclans.com/badges/512/qvVyEGEhwIjPx6oL_BYwfcnp_hoVPWhbBaWGJdsAnpQ.png",
      "medium": "https://api-assets.clashofclans.com/badges/200/qvVyEGEhwIjPx6oL_BYwfcnp_hoVPWhbBaWGJdsAnpQ.png"
    },
    "clanLevel": 16,
    "attacks": 47,
    "stars": 86,
    "destructionPercentage": 98.73333,
    "members": [
      {
        "tag": "#QVGUGCL2",
        "name": "Biscuit_08",
        "townhallLevel": 14,
        "mapPosition": 21,
        "opponentAttacks": 3,
        "bestOpponentAttack": {
          "attackerTag": "#LLYV29CU",
          "defenderTag": "#QVGUGCL2",
          "stars": 2,
          "destructionPercentage": 92,
          "order": 82,
          "duration": 180
        }
      },
      {
        "tag": "#9QC0YY9J8",
        "name": "Kosumo",
        "townhallLevel": 14,
        "mapPosition": 15,
        "attacks": [
          {
            "attackerTag": "#9QC0YY9J8",
            "defenderTag": "#9VU0VU90G",
            "stars": 3,
            "destructionPercentage": 100,
            "order": 79,
            "duration": 69
          },
          {
            "attackerTag": "#9QC0YY9J8",
            "defenderTag": "#QVUQ2VR98",
            "stars": 3,
            "destructionPercentage": 100,
            "order": 81,
            "duration": 73
          }
        ],
        "opponentAttacks": 2,
        "bestOpponentAttack": {
          "attackerTag": "#LCUL88JLG",
          "defenderTag": "#9QC0YY9J8",
          "stars": 3,
          "destructionPercentage": 100,
          "order": 72,
          "duration": 147
        }
      },
      {
        "tag": "#PGPQCCVJ",
        "name": "Bad Boy",
        "townhallLevel": 15,
        "mapPosition": 9,
        "attacks": [
          {
            "attackerTag": "#PGPQCCVJ",
            "defenderTag": "#99JUYVYLC",
            "stars": 3,
            "destructionPercentage": 100,
            "order": 18,
            "duration": 127
          },
          {
            "attackerTag": "#PGPQCCVJ",
            "defenderTag": "#LYJJ9PLV9",
            "stars": 3,
            "destructionPercentage": 100,
            "order": 25,
            "duration": 139
          }
        ],
        "opponentAttacks": 1,
        "bestOpponentAttack": {
          "attackerTag": "#Q9QU8L8YV",
          "defenderTag": "#PGPQCCVJ",
          "stars": 3,
          "destructionPercentage": 100,
          "order": 44,
          "duration": 165
        }
      },
      {
        "tag": "#QQUPP29VC",
        "name": "DRAGON KING",
        "townhallLevel": 14,
        "mapPosition": 26,
        "attacks": [
          {
            "attackerTag": "#QQUPP29VC",
            "defenderTag": "#QRP2RLV02",
            "stars": 1,
            "destructionPercentage": 76,
            "order": 64,
            "duration": 128
          },
          {
            "attackerTag": "#QQUPP29VC",
            "defenderTag": "#Q2QQL2YVV",
            "stars": 2,
            "destructionPercentage": 87,
            "order": 65,
            "duration": 178
          }
        ],
        "opponentAttacks": 1,
        "bestOpponentAttack": {
          "attackerTag": "#2920V9PV",
          "defenderTag": "#QQUPP29VC",
          "stars": 2,
          "destructionPercentage": 87,
          "order": 40,
          "duration": 128
        }
      },
      {
        "tag": "#YUUGYLL8",
        "name": "evan2",
        "townhallLevel": 14,
        "mapPosition": 27,
        "attacks": [
          {
            "attackerTag": "#YUUGYLL8",
            "defenderTag": "#RJULR9R",
            "stars": 3,
            "destructionPercentage": 100,
            "order": 28,
            "duration": 110
          }
        ],
        "opponentAttacks": 4,
        "bestOpponentAttack": {
          "attackerTag": "#9VU0VU90G",
          "defenderTag": "#YUUGYLL8",
          "stars": 2,
          "destructionPercentage": 91,
          "order": 74,
          "duration": 140
        }
      },
      {
        "tag": "#8LUYJYPLV",
        "name": "Supercookie",
        "townhallLevel": 16,
        "mapPosition": 3,
        "attacks": [
          {
            "attackerTag": "#8LUYJYPLV",
            "defenderTag": "#UJP2UYRY",
            "stars": 3,
            "destructionPercentage": 100,
            "order": 55,
            "duration": 87
          },
          {
            "attackerTag": "#8LUYJYPLV",
            "defenderTag": "#Q9QU8L8YV",
            "stars": 3,
            "destructionPercentage": 100,
            "order": 56,
            "duration": 64
          }
        ],
        "opponentAttacks": 1,
        "bestOpponentAttack": {
          "attackerTag": "#YQ8L9JVJ2",
          "defenderTag": "#8LUYJYPLV",
          "stars": 3,
          "destructionPercentage": 100,
          "order": 12,
          "duration": 155
        }
      },
      {
        "tag": "#QYCYV9Q2G",
        "name": "zwuwuww",
        "townhallLevel": 14,
        "mapPosition": 22,
        "opponentAttacks": 1,
        "bestOpponentAttack": {
          "attackerTag": "#Q2QQL2YVV",
          "defenderTag": "#QYCYV9Q2G",
          "stars": 3,
          "destructionPercentage": 100,
          "order": 50,
          "duration": 127
        }
      },
      {
        "tag": "#G2Y8R0QCL",
        "name": "Ayush",
        "townhallLevel": 14,
        "mapPosition": 23,
        "attacks": [
          {
            "attackerTag": "#G2Y8R0QCL",
            "defenderTag": "#Q2QQL2YVV",
            "stars": 2,
            "destructionPercentage": 95,
            "order": 83,
            "duration": 166
          },
          {
            "attackerTag": "#G2Y8R0QCL",
            "defenderTag": "#G9CC9G2VQ",
            "stars": 1,
            "destructionPercentage": 94,
            "order": 85,
            "duration": 171
          }
        ],
        "opponentAttacks": 1,
        "bestOpponentAttack": {
          "attackerTag": "#LPYV8PPGP",
          "defenderTag": "#G2Y8R0QCL",
          "stars": 3,
          "destructionPercentage": 100,
          "order": 31,
          "duration": 141
        }
      },
      {
        "tag": "#9VRLVPPYQ",
        "name": "Endric",
        "townhallLevel": 13,
        "mapPosition": 30,
        "attacks": [
          {
            "attackerTag": "#9VRLVPPYQ",
            "defenderTag": "#V0JYCPRR",
            "stars": 3,
            "destructionPercentage": 100,
            "order": 5,
            "duration": 106
          },
          {
            "attackerTag": "#9VRLVPPYQ",
            "defenderTag": "#GGYGQ8098",
            "stars": 3,
            "destructionPercentage": 100,
            "order": 9,
            "duration": 82
          }
        ],
        "opponentAttacks": 2,
        "bestOpponentAttack": {
          "attackerTag": "#RUVPQQR0",
          "defenderTag": "#9VRLVPPYQ",
          "stars": 3,
          "destructionPercentage": 100,
          "order": 38,
          "duration": 144
        }
      },
      {
        "tag": "#QLJ888P0",
        "name": "Grumpers",
        "townhallLevel": 15,
        "mapPosition": 5,
        "opponentAttacks": 1,
        "bestOpponentAttack": {
          "attackerTag": "#UJP2UYRY",
          "defenderTag": "#QLJ888P0",
          "stars": 3,
          "destructionPercentage": 100,
          "order": 43,
          "duration": 113
        }
      },
      {
        "tag": "#2JG8G0GUC",
        "name": "SEN",
        "townhallLevel": 14,
        "mapPosition": 13,
        "attacks": [
          {
            "attackerTag": "#2JG8G0GUC",
            "defenderTag": "#LCUL88JLG",
            "stars": 2,
            "destructionPercentage": 99,
            "order": 29,
            "duration": 180
          },
          {
            "attackerTag": "#2JG8G0GUC",
            "defenderTag": "#2920V9PV",
            "stars": 3,
            "destructionPercentage": 100,
            "order": 30,
            "duration": 133
          }
        ],
        "opponentAttacks": 2,
        "bestOpponentAttack": {
          "attackerTag": "#9U2YP0RY",
          "defenderTag": "#2JG8G0GUC",
          "stars": 3,
          "destructionPercentage": 100,
          "order": 71,
          "duration": 99
        }
      },
      {
        "tag": "#YC2Q220G",
        "name": "Mason",
        "townhallLevel": 14,
        "mapPosition": 24,
        "attacks": [
          {
            "attackerTag": "#YC2Q220G",
            "defenderTag": "#Q9Q0CRR0V",
            "stars": 3,
            "destructionPercentage": 100,
            "order": 78,
            "duration": 118
          },
          {
            "attackerTag": "#YC2Q220G",
            "defenderTag": "#LCUL88JLG",
            "stars": 2,
            "destructionPercentage": 86,
            "order": 80,
            "duration": 161
          }
        ],
        "opponentAttacks": 1,
        "bestOpponentAttack": {
          "attackerTag": "#Q0YQURYCY",
          "defenderTag": "#YC2Q220G",
          "stars": 2,
          "destructionPercentage": 52,
          "order": 36,
          "duration": 93
        }
      },
      {
        "tag": "#L8VG2VC0L",
        "name": "Ishka",
        "townhallLevel": 15,
        "mapPosition": 7,
        "attacks": [
          {
            "attackerTag": "#L8VG2VC0L",
            "defenderTag": "#9GL0YG0VU",
            "stars": 2,
            "destructionPercentage": 82,
            "order": 20,
            "duration": 161
          },
          {
            "attackerTag": "#L8VG2VC0L",
            "defenderTag": "#LPYV8PPGP",
            "stars": 3,
            "destructionPercentage": 100,
            "order": 21,
            "duration": 165
          }
        ],
        "opponentAttacks": 1,
        "bestOpponentAttack": {
          "attackerTag": "#LYJJ9PLV9",
          "defenderTag": "#L8VG2VC0L",
          "stars": 3,
          "destructionPercentage": 100,
          "order": 69,
          "duration": 163
        }
      },
      {
        "tag": "#GJJPC9QV",
        "name": "TX",
        "townhallLevel": 14,
        "mapPosition": 18,
        "attacks": [
          {
            "attackerTag": "#GJJPC9QV",
            "defenderTag": "#9VU0VU90G",
            "stars": 2,
            "destructionPercentage": 84,
            "order": 1,
            "duration": 141
          },
          {
            "attackerTag": "#GJJPC9QV",
            "defenderTag": "#QRP2RLV02",
            "stars": 3,
            "destructionPercentage": 100,
            "order": 66,
            "duration": 130
          }
        ],
        "opponentAttacks": 1,
        "bestOpponentAttack": {
          "attackerTag": "#LCUL88JLG",
          "defenderTag": "#GJJPC9QV",
          "stars": 3,
          "destructionPercentage": 100,
          "order": 70,
          "duration": 138
        }
      },
      {
        "tag": "#9VGCJC0GC",
        "name": "dx generation",
        "townhallLevel": 13,
        "mapPosition": 29,
        "attacks": [
          {
            "attackerTag": "#9VGCJC0GC",
            "defenderTag": "#Q9Q0CRR0V",
            "stars": 2,
            "destructionPercentage": 86,
            "order": 33,
            "duration": 180
          },
          {
            "attackerTag": "#9VGCJC0GC",
            "defenderTag": "#RUVPQQR0",
            "stars": 3,
            "destructionPercentage": 100,
            "order": 34,
            "duration": 158
          }
        ],
        "opponentAttacks": 3,
        "bestOpponentAttack": {
          "attackerTag": "#G9CC9G2VQ",
          "defenderTag": "#9VGCJC0GC",
          "stars": 3,
          "destructionPercentage": 100,
          "order": 57,
          "duration": 110
        }
      },
      {
        "tag": "#PP8RGVJY0",
        "name": "DANTE",
        "townhallLevel": 14,
        "mapPosition": 16,
        "attacks": [
          {
            "attackerTag": "#PP8RGVJY0",
            "defenderTag": "#GLU9LC2LG",
            "stars": 1,
            "destructionPercentage": 79,
            "order": 32,
            "duration": 134
          }
        ],
        "opponentAttacks": 2,
        "bestOpponentAttack": {
          "attackerTag": "#QRP2RLV02",
          "defenderTag": "#PP8RGVJY0",
          "stars": 3,
          "destructionPercentage": 100,
          "order": 58,
          "duration": 128
        }
      },
      {
        "tag": "#280Y2VPL2",
        "name": "Armain",
        "townhallLevel": 15,
        "mapPosition": 4,
        "attacks": [
          {
            "attackerTag": "#280Y2VPL2",
            "defenderTag": "#LYJJ9PLV9",
            "stars": 2,
            "destructionPercentage": 90,
            "order": 6,
            "duration": 180
          },
          {
            "attackerTag": "#280Y2VPL2",
            "defenderTag": "#9U2YP0RY",
            "stars": 3,
            "destructionPercentage": 100,
            "order": 8,
            "duration": 149
          }
        ],
        "opponentAttacks": 1,
        "bestOpponentAttack": {
          "attackerTag": "#YQ8L9JVJ2",
          "defenderTag": "#280Y2VPL2",
          "stars": 3,
          "destructionPercentage": 100,
          "order": 15,
          "duration": 163
        }
      },
      {
        "tag": "#P290YCJ2L",
        "name": "AK 101",
        "townhallLevel": 14,
        "mapPosition": 28,
        "attacks": [
          {
            "attackerTag": "#P290YCJ2L",
            "defenderTag": "#QQUUQYQVL",
            "stars": 2,
            "destructionPercentage": 99,
            "order": 22,
            "duration": 180
          },
          {
            "attackerTag": "#P290YCJ2L",
            "defenderTag": "#YRPCLRRLQ",
            "stars": 3,
            "destructionPercentage": 100,
            "order": 23,
            "duration": 128
          }
        ],
        "opponentAttacks": 2,
        "bestOpponentAttack": {
          "attackerTag": "#Q9Q0CRR0V",
          "defenderTag": "#P290YCJ2L",
          "stars": 2,
          "destructionPercentage": 55,
          "order": 42,
          "duration": 79
        }
      },
      {
        "tag": "#2VYP99Q0",
        "name": "Sofia",
        "townhallLevel": 14,
        "mapPosition": 14,
        "attacks": [
          {
            "attackerTag": "#2VYP99Q0",
            "defenderTag": "#Q2QQL2YVV",
            "stars": 3,
            "destructionPercentage": 100,
            "order": 84,
            "duration": 146
          },
          {
            "attackerTag": "#2VYP99Q0",
            "defenderTag": "#Q0YQURYCY",
            "stars": 3,
            "destructionPercentage": 100,
            "order": 86,
            "duration": 96
          }
        ],
        "opponentAttacks": 2,
        "bestOpponentAttack": {
          "attackerTag": "#LYJJ9PLV9",
          "defenderTag": "#2VYP99Q0",
          "stars": 3,
          "destructionPercentage": 100,
          "order": 90,
          "duration": 160
        }
      },
      {
        "tag": "#2UYQQ288J",
        "name": "Moose",
        "townhallLevel": 14,
        "mapPosition": 11,
        "attacks": [
          {
            "attackerTag": "#2UYQQ288J",
            "defenderTag": "#GLU9LC2LG",
            "stars": 3,
            "destructionPercentage": 100,
            "order": 67,
            "duration": 167
          },
          {
            "attackerTag": "#2UYQQ288J",
            "defenderTag": "#QVUQ2VR98",
            "stars": 2,
            "destructionPercentage": 99,
            "order": 76,
            "duration": 180
          }
        ],
        "opponentAttacks": 1,
        "bestOpponentAttack": {
          "attackerTag": "#9GL0YG0VU",
          "defenderTag": "#2UYQQ288J",
          "stars": 3,
          "destructionPercentage": 100,
          "order": 48,
          "duration": 148
        }
      },
      {
        "tag": "#LP90C2YPP",
        "name": "brave",
        "townhallLevel": 17,
        "mapPosition": 2,
        "attacks": [
          {
            "attackerTag": "#LP90C2YPP",
            "defenderTag": "#YQ8L9JVJ2",
            "stars": 2,
            "destructionPercentage": 63,
            "order": 11,
            "duration": 130
          },
          {
            "attackerTag": "#LP90C2YPP",
            "defenderTag": "#UJP2UYRY",
            "stars": 2,
            "destructionPercentage": 79,
            "order": 13,
            "duration": 156
          }
        ],
        "opponentAttacks": 1,
        "bestOpponentAttack": {
          "attackerTag": "#G28CVVRJL",
          "defenderTag": "#LP90C2YPP",
          "stars": 3,
          "destructionPercentage": 100,
          "order": 10,
          "duration": 156
        }
      },
      {
        "tag": "#GJJJJ8QJ2",
        "name": "jewel",
        "townhallLevel": 15,
        "mapPosition": 6,
        "attacks": [
          {
            "attackerTag": "#GJJJJ8QJ2",
            "defenderTag": "#Q9QU8L8YV",
            "stars": 2,
            "destructionPercentage": 80,
            "order": 19,
            "duration": 112
          },
          {
            "attackerTag": "#GJJJJ8QJ2",
            "defenderTag": "#QVGVJJ99C",
            "stars": 3,
            "destructionPercentage": 100,
            "order": 24,
            "duration": 92
          }
        ],
        "opponentAttacks": 1,
        "bestOpponentAttack": {
          "attackerTag": "#UJP2UYRY",
          "defenderTag": "#GJJJJ8QJ2",
          "stars": 3,
          "destructionPercentage": 100,
          "order": 45,
          "duration": 73
        }
      },
      {
        "tag": "#QGCC80GC8",
        "name": "InfamousPanda15",
        "townhallLevel": 17,
        "mapPosition": 1,
        "attacks": [
          {
            "attackerTag": "#QGCC80GC8",
            "defenderTag": "#YQ8L9JVJ2",
            "stars": 3,
            "destructionPercentage": 100,
            "order": 87,
            "duration": 176
          },
          {
            "attackerTag": "#QGCC80GC8",
            "defenderTag": "#G28CVVRJL",
            "stars": 2,
            "destructionPercentage": 82,
            "order": 88,
            "duration": 154
          }
        ],
        "opponentAttacks": 1,
        "bestOpponentAttack": {
          "attackerTag": "#G28CVVRJL",
          "defenderTag": "#QGCC80GC8",
          "stars": 3,
          "destructionPercentage": 100,
          "order": 3,
          "duration": 144
        }
      },
      {
        "tag": "#9CRY00G00",
        "name": "mikki",
        "townhallLevel": 15,
        "mapPosition": 8,
        "attacks": [
          {
            "attackerTag": "#9CRY00G00",
            "defenderTag": "#LGGLYVUPP",
            "stars": 3,
            "destructionPercentage": 100,
            "order": 2,
            "duration": 126
          },
          {
            "attackerTag": "#9CRY00G00",
            "defenderTag": "#PPLULPGVU",
            "stars": 3,
            "destructionPercentage": 100,
            "order": 4,
            "duration": 142
          }
        ],
        "opponentAttacks": 1,
        "bestOpponentAttack": {
          "attackerTag": "#Q9QU8L8YV",
          "defenderTag": "#9CRY00G00",
          "stars": 3,
          "destructionPercentage": 100,
          "order": 47,
          "duration": 162
        }
      },
      {
        "tag": "#YLUGJYP00",
        "name": "Ender",
        "townhallLevel": 14,
        "mapPosition": 20,
        "attacks": [
          {
            "attackerTag": "#YLUGJYP00",
            "defenderTag": "#Q0YQURYCY",
            "stars": 2,
            "destructionPercentage": 70,
            "order": 62,
            "duration": 129
          },
          {
            "attackerTag": "#YLUGJYP00",
            "defenderTag": "#G9CC9G2VQ",
            "stars": 2,
            "destructionPercentage": 91,
            "order": 63,
            "duration": 127
          }
        ],
        "opponentAttacks": 1,
        "bestOpponentAttack": {
          "attackerTag": "#QVUQ2VR98",
          "defenderTag": "#YLUGJYP00",
          "stars": 2,
          "destructionPercentage": 92,
          "order": 53,
          "duration": 112
        }
      },
      {
        "tag": "#YP9Y8U0QC",
        "name": "abdaal",
        "townhallLevel": 14,
        "mapPosition": 25,
        "attacks": [
          {
            "attackerTag": "#YP9Y8U0QC",
            "defenderTag": "#G9CC9G2VQ",
            "stars": 2,
            "destructionPercentage": 93,
            "order": 89,
            "duration": 128
          }
        ],
        "opponentAttacks": 2,
        "bestOpponentAttack": {
          "attackerTag": "#QRP2RLV02",
          "defenderTag": "#YP9Y8U0QC",
          "stars": 3,
          "destructionPercentage": 100,
          "order": 59,
          "duration": 72
        }
      },
      {
        "tag": "#L0QG2V09",
        "name": "F\u00e3h\u00eem",
        "townhallLevel": 14,
        "mapPosition": 17,
        "opponentAttacks": 1,
        "bestOpponentAttack": {
          "attackerTag": "#LGGLYVUPP",
          "defenderTag": "#L0QG2V09",
          "stars": 2,
          "destructionPercentage": 90,
          "order": 27,
          "duration": 107
        }
      },
      {
        "tag": "#P0RRULRP9",
        "name": "Arun",
        "townhallLevel": 14,
        "mapPosition": 19,
        "opponentAttacks": 2,
        "bestOpponentAttack": {
          "attackerTag": "#99JUYVYLC",
          "defenderTag": "#P0RRULRP9",
          "stars": 3,
          "destructionPercentage": 100,
          "order": 75,
          "duration": 145
        }
      },
      {
        "tag": "#L8L0U9QJL",
        "name": "Obito",
        "townhallLevel": 14,
        "mapPosition": 12,
        "attacks": [
          {
            "attackerTag": "#L8L0U9QJL",
            "defenderTag": "#2QRGJQJ2Q",
            "stars": 3,
            "destructionPercentage": 100,
            "order": 52,
            "duration": 142
          },
          {
            "attackerTag": "#L8L0U9QJL",
            "defenderTag": "#LLYV29CU",
            "stars": 3,
            "destructionPercentage": 100,
            "order": 60,
            "duration": 146
          }
        ],
        "opponentAttacks": 1,
        "bestOpponentAttack": {
          "attackerTag": "#GLU9LC2LG",
          "defenderTag": "#L8L0U9QJL",
          "stars": 3,
          "destructionPercentage": 100,
          "order": 14,
          "duration": 145
        }
      },
      {
        "tag": "#2QG8JYCGG",
        "name": "SHIWANG",
        "townhallLevel": 15,
        "mapPosition": 10,
        "attacks": [
          {
            "attackerTag": "#2QG8JYCGG",
            "defenderTag": "#9GL0YG0VU",
            "stars": 2,
            "destructionPercentage": 82,
            "order": 91,
            "duration": 101
          },
          {
            "attackerTag": "#2QG8JYCGG",
            "defenderTag": "#G9CC9G2VQ",
            "stars": 3,
            "destructionPercentage": 100,
            "order": 92,
            "duration": 72
          }
        ],
        "opponentAttacks": 1,
        "bestOpponentAttack": {
          "attackerTag": "#9U2YP0RY",
          "defenderTag": "#2QG8JYCGG",
          "stars": 3,
          "destructionPercentage": 100,
          "order": 68,
          "duration": 73
        }
      }
    ]
  }
}